aws_s3_controller/__init__.py
aws_s3_controller/alias.py
aws_s3_controller/aws_connector.py
aws_s3_controller/aws_consts.py
aws_s3_controller/s3_dataframe_reader.py
aws_s3_controller/s3_scanner.py
aws_s3_controller/s3_special_operations.py
aws_s3_controller/s3_structure.py
aws_s3_controller/s3_transfer.py
aws_s3_controller-0.7.5.dist-info/LICENSE
aws_s3_controller-0.7.5.dist-info/METADATA
aws_s3_controller-0.7.5.dist-info/WHEEL
aws_s3_controller-0.7.5.dist-info/top_level.txt
aws_s3_controller-0.7.5.dist-info/RECORD
