Metadata-Version: 2.2
Name: aws_s3_controller
Version: 0.7.5
Summary: A collection of natural language-like utility functions to intuitively and easily control AWS's cloud object storage resource, S3.
Home-page: https://github.com/nailen1/aws_s3_controller.git
Author: June Young Park
Author-email: juneyoungpaak@gmail.com
Keywords: aws s3 storage file-management data-processing
Classifier: Development Status :: 4 - Beta
Classifier: Intended Audience :: Developers
Classifier: Topic :: Software Development :: Libraries :: Python Modules
Classifier: Programming Language :: Python :: 3
Classifier: Programming Language :: Python :: 3.7
Classifier: Programming Language :: Python :: 3.8
Classifier: Programming Language :: Python :: 3.9
Classifier: Programming Language :: Python :: 3.10
Classifier: License :: OSI Approved :: MIT License
Classifier: Operating System :: OS Independent
Requires-Python: >=3.7
License-File: LICENSE
Requires-Dist: boto3>=1.26.0
Requires-Dist: python-dotenv>=1.0.0
Requires-Dist: pandas>=1.3.0
Requires-Dist: xlrd>=2.0.1
Requires-Dist: shining_pebbles
Requires-Dist: string_date_controller>=0.1.1
Dynamic: author
Dynamic: author-email
Dynamic: classifier
Dynamic: description
Dynamic: description-content-type
Dynamic: home-page
Dynamic: keywords
Dynamic: requires-dist
Dynamic: requires-python
Dynamic: summary
